pyscr/__init__.py
pyscr-0.1.dist-info/METADATA
pyscr-0.1.dist-info/WHEEL
pyscr-0.1.dist-info/top_level.txt
pyscr-0.1.dist-info/RECORD
