Metadata-Version: 2.1
Name: pyscr
Version: 0.1
Summary: A Python library for RNAseq analysis
Home-page: https://github.com/aneeshpanoli/pyscr
Author: Aneesh aneeshpanoli
Author-email: topanoli@gmail.com
License: MIT
Platform: UNKNOWN
